{"GEEDZHmcXjL1jOnGGkxnAg==":"logo-no-bg-96x48.png","VxanVX2l2Nbej4ChCC8B3A==":"beach_access.svg","Qwf5bTkn3O4nMJw/sYhXNw==":"balcony.svg","NJRJrDemVFxfUWzDa9Ja+g==":"outdoor_grill.svg","DZ+5XCiU7UXgaoRbM3F8kg==":"parking_sign.svg","9HwmaOD0QXBvCZr/ZeBygA==":"pets.svg","6cbwBSfWWR8/p7SE6nynKw==":"featured_seasonal_and_gifts.svg","H+VIpEqJAuQfJTzchXK1LQ==":"primosten-image-1-600x748.jpeg","kUc7rmOuNd9sVS1NpF4vQw==":"rogoznica2-image.webp","I6l+6epUc7nac0xrEUYRsQ==":"trogir-image-600x400.jpeg","teQkbDzSpFt/Vda9L7LKdw==":"sibenik-image-1000x667.jpeg","Z73r9RHKfhRHwJh5A6MiKQ==":"krka-image-1200x834.jpeg","EG7+ESGkU0OjJ4o811x8xA==":"split-image-960x740.jpeg","Fh6HKsgWVmDnzmlbRYqboA==":"main-gal-1-1274x784.jpg","Ejo42LwV3JhCd8ThvPxmJg==":"main-gal-2-1800x549.png","+IpnDPSmRvh/cEIw8m7J/g==":"main-gal-3-1800x1350.jpg","n8IWtzOqc07mM5EBd3vyUQ==":"oliveo-restaurant-ra%25c5%25beanj-rogoznica-507x362.png","v6wjIM7r87Z4HVt3YxVesA==":"mulo-cafe-ra%25c5%25beanj-rogoznica-507x607.png","+IVJDsnEiewi6SfqAB+25Q==":"studenac-market-ra%25c5%25beanj-rogoznica-507x362.png","pu9xYW802Qwnaemj1ht7CQ==":"2-704x1252.jpeg","FVFCciu2zANBh6qW1iR65Q==":"balcony3-704x939.jpeg","LBeKEEVBcM0q2nc8Ji4Wbw==":"indoor2-704x528.jpg","q/3nNd3dVYw9MDlgiZNP9A==":"indoor1-704x528.jpg","iHuVa/60qClSde1hgOUBjw==":"indoor3-704x528.jpg","94QfpQTThSoM9LtlV2VFrA==":"garden3-1-704x1251.jpeg","7t0dQh87adhfWMkWNLCuzQ==":"3-704x704.jpg","/ksWTDUPSzu63BNhyVYOYA==":"lagoonica-seaside-apartment-rogoznica-beach-5-2000x1500.jpg","Nh/cuu7f3D3AbFbiUjdGrA==":"%25e2%2598%2585%25e2%2598%2585%25e2%2598%2585%25e2%2598%2585%25e2%2598%2585-512x512.png","omQE4RSiV4+E6GOrTVSWTw==":"%25e2%2598%2585%25e2%2598%2585%25e2%2598%2585%25e2%2598%2585%25e2%2598%2585-512x512.png","Hr55QRGSRUzmHbSU62P0cA==":"%25e2%2598%2585%25e2%2598%2585%25e2%2598%2585%25e2%2598%2585%25e2%2598%2586-512x512.png","+U2c/qV+yR0DfJo1QKD5qw==":"%25e2%2598%2585%25e2%2598%2585%25e2%2598%2585%25e2%2598%2585%25e2%2598%2585-lg-512x512.png","HHVKC5JxakkZynPtNij/lg==":"mbr.jpg","CwCfuhTXJFvr4XP3gfM5Ow==":"mbr-2.jpg","U72176xIYxCMs6QDt73J1Q==":"mbr-3.jpg","sSiDy6Pu9naF4IVHxTlJtw==":"rogoznica-near-ibenik.jpg","TcYaNNrLwgUSROE04yBu9w==":"mbr-4.jpg","idDqJreVGtob/2QFQUtOQg==":"lagoonica-seaside-apartment-rogoznica-terrace-beach-view.jpg","UfjBhrRSecgIo4eJwEh4ag==":"lagoonica-seaside-apartment-rogoznica-garden.jpeg","Z61Qefe597rMnqIgq3OeQQ==":"lagoonica-seaside-apartment-rogoznica-garden-2.jpeg","m3yUzNlarHJL0Os6EzM6Gg==":"lagoonica-seaside-apartment-rogoznica-living-room.jpeg","np5wGETpsVeNS6z/RwgBzQ==":"lagoonica-seaside-apartment-rogoznica-living-room-kitchen.jpeg","5fspKZusQizN0LonuQopyg==":"lagoonica-seaside-apartment-rogoznica-living-bathroom.jpeg","KgsYYXQObSjvg70gBHf1QQ==":"lagoonica-seaside-apartment-rogoznica-living-bedroom.jpeg","iKTQJVDw3RP/XFYG7BGsJQ==":"lagoonica-seaside-apartment-rogoznica-balcony.jpeg","LHe5hF8SLtI2nu9yAlFahg==":"lagoonica-seaside-apartment-rogoznica-terrace-and-wine.jpeg","44iP4KQlPwaxmY2EBWfAZA==":"lagoonica-seaside-apartment-rogoznica-bbq-3.jpeg","rxn15lf0aEcgq16KWy3OUQ==":"lagoonica-seaside-apartment-rogoznica-beach.jpg","ar3yOt3G6HwiMscaJ4e4fg==":"lagoonica-seaside-apartment-rogoznica-beach-sunset.jpg","gTYApyXNANjJZBK2c9wS/g==":"lagoonica-seaside-apartment-rogoznica-beach-2.jpg","/ZVfv48hbr8Q/0vTF3sS7g==":"lagoonica-seaside-apartment-rogoznica-beach-cocktail.jpg","JpmT+cN8ZbsTocIvlK0KYA==":"kopara1.jpeg","gUypdTsganaQJ5TnNh3OSA==":"lavander1.jpeg","b12yILAKu/1L6mDyZCxHTA==":"movar.jpeg","VPZjmTLm5JjKA33qQrDFmw==":"dragon-eye.jpeg","YPkCstnoNI9+tKwvqheMjg==":"5.png","z8lkq0v1jbiM0vGouy9izw==":"lagoonica-seaside-apartment-rogoznica-guests-beach-2.jpeg","Z+9JOt0JO6Whk3VruHHULQ==":"lagoonica-seaside-apartment-rogoznica-guests-beach.jpg","AZ6fh5ChlHPQmYsTT12u7g==":"lagoonica-seaside-apartment-rogoznica-pets-sunset.jpg","7R66gD/Wf2FdXdDQ+N2paA==":"lagoonica-seaside-apartment-rogoznica-guests.jpeg","mp+cFwoNYwzRdny/lEuHRg==":"lagoonica-seaside-apartment-rogoznica-guests-beach-4.jpeg","kkToSAc7R7dMs0XFwNkRgw==":"lagoonica-seaside-apartment-rogoznica-panorama.jpeg","tfHG0w2kYTcMBy8VvTDRDA==":"lagoonica-seaside-apartment-rogoznica-living-bathroom-1.jpeg","UXQuRoBAExPuaDAPD90z9Q==":"lagoonica-seaside-apartment-rogoznica-balcony-2.jpeg","8NpjzMsweXUgTORjEgMDgg==":"2.jpg","o7NAZAcp1hBOYkZ3YgtR5A==":"mbr-7.jpg","yL9U4JNrl8wYhOIcTgp0dA==":"coastal-road-overlooking-adriatic-sea.jpeg","nz6zd+VynTyDCpCb6q5c8g==":"mbr-1.png","sdyc51DQjOeMUxrsnMoUSg==":"mbr-1.jpeg","BoHM30yH3p3IKwipUodRtw==":"mbr-2.jpeg","4VcT0PDm0iO3CkFNj+dp6A==":"mbr-3.jpeg","DAvE77U7Cr0zJb+fScNgpw==":"bread.jpeg","xUHX79IIHI4+ZyaXHm3rag==":"fruit-vegetables.jpeg","W03UcymET28RwJT+otvMyQ==":"ice-cream.jpeg","NvLZDaub3X6adPAxzsMpSg==":"local-deliveries-bread-fruit-fish.png","MOg7gBf7NO6/koM2jrwCRQ==":"mbr.jpeg","MFBambqVL5QOr1J7lpDxWA==":"aplit-international-airport.png","lShup8FL9VN1Cd4pgHcv4Q==":"taxi-boat-rogoznica.jpeg","YpKWBbGFlC/p5I7v+64FYg==":"mbr-1.jpg","kMBYUvn7VuKDJqPOXn3efw==":"beach3.jpeg","IDhALEtxER7N+QaO6ez1JA==":"beach3-1.jpeg","lJy8cbDlEyHlnWP4KXcCXQ==":"mbr-5.jpg","ja2yFS0JtdmG1j8dJi1CyQ==":"mbr-5.jpeg","ACB8Pj2/ed83IvxFgBxMFQ==":"mbr-6.jpg","gpDOAZ8RT8RY7VbSF5cDTw==":"mbr-4.jpeg","QQ/Zw7HYE0RHv9ivaHGd4w==":"mbr-6.jpeg","qoiI8Dq20VlUjSvQ9AeeiA==":"mbr-8.jpg","XwR4Af/TnFy+KoCRigYylg==":"mbr-8.jpeg","F1GJTIEudW6XKpKX3+A9NQ==":"taxi-boat-rogoznica-1.jpeg","S5g86vhhcdf1cfhVri9Oeg==":"kids-trampoline-jumping.jpg","rDWSqUuwEevBvFjOOmiB3A==":"mbr-9.jpg","8ABg9nl4qBl2DCY9I3FGlw==":"rogoznica-water-park.jpg","uaLW66qXlbvN4gFmzJVXJA==":"rogoznica-water-park.jpeg","pS1xVVznKg9i8U2NaHQ3zQ==":"rogoznica-aqua-park.jpeg","ycEzsbMpoO+H3z3n+qFSkA==":"paddle-board-rogoznica.jpeg","kLX5e7FW/IC0n+D4CLN5Rw==":"beach-massage-rogoznica.jpg","taAshQ/KPsQMzDx6El8c0A==":"mbr-10.jpg","wO63envaPJD8Wj4ng3hk2A==":"mini-train-tour.jpg","pDvnoZyXI5CtDssjQxGgWg==":"rogoznica-aqua-park.jpg","r1ttdg+ClDdQ+ZejvPnLwA==":"taxi-boat-rogoznica.jpg","bctxxwuVlyWUj+wU0s+Atg==":"mbr-11.jpg","+3krHysPrUddhIFVTiaRkA==":"mbr-12.jpg","selAnx8NsMd2oHjsjDaadg==":"mbr-12.jpeg","5DczAOb2E5avWnuxX7cHAg==":"mbr-13.jpg","uQW7UAdMocCIisKisZOu+g==":"mbr-14.jpg","Nhwx0T/rNZQEhOJQmwgIGw==":"mbr-15.jpg","okF3PpPtVl56VcPFUzg3/w==":"mbr-16.jpg"}